memorymanagement/__init__.py
memorymanagement/cleaning/__init__.py
memorymanagement/cleaning/core.py
memorymanagement/pointers/__init__.py
memorymanagement/pointers/core.py
memorymanagement/pointers/decorators.py
memorymanagement-1.1.0.dist-info/licenses/LICENSE
memorymanagement-1.1.0.dist-info/METADATA
memorymanagement-1.1.0.dist-info/WHEEL
memorymanagement-1.1.0.dist-info/top_level.txt
memorymanagement-1.1.0.dist-info/RECORD
