Metadata-Version: 2.4
Name: memorymanagement
Version: 1.1.0
Summary: Adds support for memory management
Home-page: https://github.com/Ricardo-Werner-Rivas/python-memory-management/tree/PyPI
Author: Ricardo Werner Rivas
Author-email: ricardowernerrivas@gmail.com
License: MIT
Project-URL: Bug Tracker, https://github.com/Ricardo-Werner-Rivas/python-memory-management/issues
Project-URL: Repository, https://github.com/Ricardo-Werner-Rivas/python-memory-management
Classifier: Programming Language :: Python
Classifier: Operating System :: Microsoft :: Windows
License-File: LICENSE
Dynamic: license-file
